langchain_experimental/__init__.py
langchain_experimental/agents/__init__.py
langchain_experimental/agents/agent_toolkits/__init__.py
langchain_experimental/agents/agent_toolkits/csv/__init__.py
langchain_experimental/agents/agent_toolkits/csv/base.py
langchain_experimental/agents/agent_toolkits/pandas/__init__.py
langchain_experimental/agents/agent_toolkits/pandas/base.py
langchain_experimental/agents/agent_toolkits/pandas/prompt.py
langchain_experimental/agents/agent_toolkits/python/__init__.py
langchain_experimental/agents/agent_toolkits/python/base.py
langchain_experimental/agents/agent_toolkits/python/prompt.py
langchain_experimental/agents/agent_toolkits/spark/__init__.py
langchain_experimental/agents/agent_toolkits/spark/base.py
langchain_experimental/agents/agent_toolkits/spark/prompt.py
langchain_experimental/agents/agent_toolkits/xorbits/__init__.py
langchain_experimental/agents/agent_toolkits/xorbits/base.py
langchain_experimental/agents/agent_toolkits/xorbits/prompt.py
langchain_experimental/autonomous_agents/__init__.py
langchain_experimental/autonomous_agents/autogpt/__init__.py
langchain_experimental/autonomous_agents/autogpt/agent.py
langchain_experimental/autonomous_agents/autogpt/memory.py
langchain_experimental/autonomous_agents/autogpt/output_parser.py
langchain_experimental/autonomous_agents/autogpt/prompt.py
langchain_experimental/autonomous_agents/autogpt/prompt_generator.py
langchain_experimental/autonomous_agents/baby_agi/__init__.py
langchain_experimental/autonomous_agents/baby_agi/baby_agi.py
langchain_experimental/autonomous_agents/baby_agi/task_creation.py
langchain_experimental/autonomous_agents/baby_agi/task_execution.py
langchain_experimental/autonomous_agents/baby_agi/task_prioritization.py
langchain_experimental/autonomous_agents/hugginggpt/__init__.py
langchain_experimental/autonomous_agents/hugginggpt/hugginggpt.py
langchain_experimental/autonomous_agents/hugginggpt/repsonse_generator.py
langchain_experimental-0.3.1.dist-info/LICENSE
langchain_experimental-0.3.1.dist-info/METADATA
langchain_experimental-0.3.1.dist-info/WHEEL
langchain_experimental-0.3.1.dist-info/RECORD
