Metadata-Version: 2.1
Name: langchain-experimental
Version: 0.3.1
Summary: Building applications with LLMs through composability
Home-page: https://github.com/langchain-ai/langchain
License: MIT
Requires-Python: >=3.9,<4.0
Classifier: License :: OSI Approved :: MIT License
Classifier: Programming Language :: Python :: 3
Classifier: Programming Language :: Python :: 3.9
Classifier: Programming Language :: Python :: 3.10
Classifier: Programming Language :: Python :: 3.11
Classifier: Programming Language :: Python :: 3.12
Requires-Dist: langchain-community (>=0.3.0,<0.4.0)
Requires-Dist: langchain-core (>=0.3.5,<0.4.0)
Project-URL: Repository, https://github.com/langchain-ai/langchain
Project-URL: Release Notes, https://github.com/langchain-ai/langchain/releases?q=tag%3A%22langchain-experimental%3D%3D0%22&expanded=true
Project-URL: Source Code, https://github.com/langchain-ai/langchain/tree/master/libs/experimental
